{
  "categories": [
    {
      "id": "cloud-infrastructure",
      "name": "Cloud & Infrastructure",
      "icon": "☁️",
      "description": "Cloud platforms and infrastructure automation",
      "skills": [
        {
          "name": "Microsoft Azure",
          "level": 85,
          "experience": "4+ years",
          "techs": ["Data Lake", "HDInsight", "Data Factory", "Power BI"],
          "featured": true
        },
        {
          "name": "Infrastructure as Code",
          "level": 90,
          "experience": "5+ years",
          "techs": ["Terraform", "Ansible", "CloudFormation"],
          "featured": true
        },
        {
          "name": "Containerization",
          "level": 80,
          "experience": "3+ years",
          "techs": ["Docker", "Kubernetes", "Docker Compose"],
          "featured": false
        },
        {
          "name": "Linux Administration",
          "level": 90,
          "experience": "6+ years",
          "techs": ["Ubuntu", "CentOS", "RHEL", "Shell Scripting"],
          "featured": true
        }
      ]
    },
    {
      "id": "big-data",
      "name": "Big Data & Analytics",
      "icon": "📊",
      "description": "Large-scale data processing and analytics platforms",
      "skills": [
        {
          "name": "Apache Spark",
          "level": 85,
          "experience": "4+ years",
          "techs": ["PySpark", "Spark SQL", "Spark Streaming"],
          "featured": true
        },
        {
          "name": "Databricks",
          "level": 80,
          "experience": "3+ years",
          "techs": ["Delta Lake", "Unity Catalog", "Notebooks"],
          "featured": true
        },
        {
          "name": "Hadoop Ecosystem",
          "level": 75,
          "experience": "3+ years",
          "techs": ["HDFS", "Hive", "HBase", "Impala"],
          "featured": false
        },
        {
          "name": "Cloudera Platform",
          "level": 80,
          "experience": "3+ years",
          "techs": ["CDP", "HDP", "Ranger", "Hue"],
          "featured": false
        }
      ]
    },
    {
      "id": "programming",
      "name": "Programming & Development",
      "icon": "💻",
      "description": "Programming languages and development frameworks",
      "skills": [
        {
          "name": "Python",
          "level": 90,
          "experience": "6+ years",
          "techs": ["Pandas", "NumPy", "FastAPI", "Jupyter"],
          "featured": true
        },
        {
          "name": "SQL & Databases",
          "level": 85,
          "experience": "5+ years",
          "techs": ["T-SQL", "MySQL", "PostgreSQL", "Query Optimization"],
          "featured": false
        },
        {
          "name": "JavaScript",
          "level": 75,
          "experience": "3+ years",
          "techs": ["Node.js", "ES6+", "REST APIs"],
          "featured": false
        },
        {
          "name": "Shell Scripting",
          "level": 85,
          "experience": "5+ years",
          "techs": ["Bash", "PowerShell", "Zsh"],
          "featured": false
        }
      ]
    },
    {
      "id": "data-engineering",
      "name": "Data Engineering",
      "icon": "⚙️",
      "description": "Data pipelines and ETL/ELT processes",
      "skills": [
        {
          "name": "ETL/ELT Pipelines",
          "level": 85,
          "experience": "4+ years",
          "techs": ["Apache Airflow", "Data Factory", "Custom Python"],
          "featured": true
        },
        {
          "name": "Data Processing",
          "level": 80,
          "experience": "4+ years",
          "techs": ["Pandas", "PySpark", "Stream Processing"],
          "featured": false
        },
        {
          "name": "Data Modeling",
          "level": 75,
          "experience": "3+ years",
          "techs": ["Dimensional Modeling", "Star Schema", "Data Vault"],
          "featured": false
        },
        {
          "name": "Data Quality",
          "level": 80,
          "experience": "3+ years",
          "techs": ["Great Expectations", "Data Validation", "Testing"],
          "featured": false
        }
      ]
    },
    {
      "id": "devops",
      "name": "DevOps & Automation",
      "icon": "🔄",
      "description": "CI/CD, automation, and operational excellence",
      "skills": [
        {
          "name": "CI/CD",
          "level": 80,
          "experience": "4+ years",
          "techs": ["GitHub Actions", "Jenkins", "GitLab CI"],
          "featured": true
        },
        {
          "name": "Version Control",
          "level": 90,
          "experience": "6+ years",
          "techs": ["Git", "GitHub", "Git Flow"],
          "featured": false
        },
        {
          "name": "Monitoring & Logging",
          "level": 75,
          "experience": "3+ years",
          "techs": ["Prometheus", "Grafana", "ELK Stack"],
          "featured": false
        },
        {
          "name": "Automation",
          "level": 85,
          "experience": "5+ years",
          "techs": ["Ansible", "Python Scripts", "Cron Jobs"],
          "featured": false
        }
      ]
    },
    {
      "id": "databases",
      "name": "Databases & Storage",
      "icon": "🗄️",
      "description": "Relational, NoSQL, and data storage solutions",
      "skills": [
        {
          "name": "Relational Databases",
          "level": 85,
          "experience": "5+ years",
          "techs": ["SQL Server", "MySQL", "PostgreSQL"],
          "featured": true
        },
        {
          "name": "NoSQL",
          "level": 70,
          "experience": "2+ years",
          "techs": ["MongoDB", "HBase", "Document Stores"],
          "featured": false
        },
        {
          "name": "Data Lakes",
          "level": 80,
          "experience": "3+ years",
          "techs": ["Azure Data Lake", "Delta Lake", "Parquet"],
          "featured": false
        },
        {
          "name": "Database Design",
          "level": 75,
          "experience": "4+ years",
          "techs": ["Normalization", "Indexing", "Performance Tuning"],
          "featured": false
        }
      ]
    }
  ]
}